README.md
setup.cfg
setup.py
django_access_logger/__init__.py
django_access_logger/access_logger.py
django_access_logger/django_access_logger.py
django_access_logger.egg-info/PKG-INFO
django_access_logger.egg-info/SOURCES.txt
django_access_logger.egg-info/dependency_links.txt
django_access_logger.egg-info/not-zip-safe
django_access_logger.egg-info/top_level.txt